hyss/__init__.py
hyss/format.py
hyss/std.py
hyss-2.0.0.dist-info/LICENSE
hyss-2.0.0.dist-info/METADATA
hyss-2.0.0.dist-info/WHEEL
hyss-2.0.0.dist-info/top_level.txt
hyss-2.0.0.dist-info/RECORD
