Metadata-Version: 2.1
Name: hyss
Version: 2.0.0
Summary: High impact style sheets, empowered by python
Author-email: Charlie Paterson <Charlieed.paterson@googlemail.com>
License: MIT License
Project-URL: Homepage, https://github.com/CpaterCodes/Hyss
Keywords: css,hyss,styles,stylesheets,animations,web,full stack
Classifier: License :: OSI Approved :: MIT License
Classifier: Development Status :: 5 - Production/Stable
Classifier: Operating System :: OS Independent
Requires-Python: >=3.6
License-File: LICENSE
Provides-Extra: dev
Requires-Dist: pipenv ; extra == 'dev'
Requires-Dist: pytest ; extra == 'dev'
